kombin/Table.py
kombin/__init__.py
kombin-1.0.0.dist-info/LICENSE
kombin-1.0.0.dist-info/METADATA
kombin-1.0.0.dist-info/WHEEL
kombin-1.0.0.dist-info/top_level.txt
kombin-1.0.0.dist-info/RECORD
