Metadata-Version: 2.1
Name: kombin
Version: 1.0.0
Summary: Indexing combinations from two finite sets.
Home-page: https://github.com/pranav-ninja/KombiN
Author: Pranavkumar Patel
Author-email: code@pranav.ninja
License: MIT
Platform: UNKNOWN
Classifier: Programming Language :: Python :: 3
Classifier: License :: OSI Approved :: MIT License
Classifier: Operating System :: OS Independent
Requires-Python: >=3.6
